<?xml version="1.0" encoding="utf-8"?>
<LanguageData>

  <VFEI_VatGrownRoyalMaggot.label>RoyalMaggotr</VFEI_VatGrownRoyalMaggot.label>
  <VFEI_VatGrownRoyalMaggot.labelPlural>RoyalMaggots</VFEI_VatGrownRoyalMaggot.labelPlural>
  <VFEI_VatGrownRoyalMaggot.lifeStages.0.label>RoyalMaggot</VFEI_VatGrownRoyalMaggot.lifeStages.0.label>
  <VFEI_VatGrownRoyalMaggot.lifeStages.0.labelPlural>RoyalMaggot</VFEI_VatGrownRoyalMaggot.lifeStages.0.labelPlural>
  <VFEI_VatGrownRoyalMaggot.lifeStages.0.labelMale>samiec RoyalMaggot</VFEI_VatGrownRoyalMaggot.lifeStages.0.labelMale>
  <VFEI_VatGrownRoyalMaggot.lifeStages.0.labelMalePlural>samce RoyalMaggot</VFEI_VatGrownRoyalMaggot.lifeStages.0.labelMalePlural>
  <VFEI_VatGrownRoyalMaggot.lifeStages.0.labelFemale>samica RoyalMaggot</VFEI_VatGrownRoyalMaggot.lifeStages.0.labelFemale>
  <VFEI_VatGrownRoyalMaggot.lifeStages.0.labelFemalePlural>samice RoyalMaggot</VFEI_VatGrownRoyalMaggot.lifeStages.0.labelFemalePlural>
  <VFEI_VatGrownRoyalMaggot.lifeStages.1.label>RoyalMaggot</VFEI_VatGrownRoyalMaggot.lifeStages.1.label>
  <VFEI_VatGrownRoyalMaggot.lifeStages.1.labelPlural>RoyalMaggot</VFEI_VatGrownRoyalMaggot.lifeStages.1.labelPlural>
  <VFEI_VatGrownRoyalMaggot.lifeStages.1.labelMale>samiec RoyalMaggot</VFEI_VatGrownRoyalMaggot.lifeStages.1.labelMale>
  <VFEI_VatGrownRoyalMaggot.lifeStages.1.labelMalePlural>samce RoyalMaggot</VFEI_VatGrownRoyalMaggot.lifeStages.1.labelMalePlural>
  <VFEI_VatGrownRoyalMaggot.lifeStages.1.labelFemale>samica RoyalMaggot</VFEI_VatGrownRoyalMaggot.lifeStages.1.labelFemale>
  <VFEI_VatGrownRoyalMaggot.lifeStages.1.labelFemalePlural>samice RoyalMaggot</VFEI_VatGrownRoyalMaggot.lifeStages.1.labelFemalePlural>
  <VFEI_VatGrownRoyalMaggot.lifeStages.2.label>RoyalMaggot</VFEI_VatGrownRoyalMaggot.lifeStages.2.label>
  <VFEI_VatGrownRoyalMaggot.lifeStages.2.labelPlural>RoyalMaggot</VFEI_VatGrownRoyalMaggot.lifeStages.2.labelPlural>
  <VFEI_VatGrownRoyalMaggot.lifeStages.2.labelMale>RoyalMaggot</VFEI_VatGrownRoyalMaggot.lifeStages.2.labelMale>
  <VFEI_VatGrownRoyalMaggot.lifeStages.2.labelMalePlural>RoyalMaggot</VFEI_VatGrownRoyalMaggot.lifeStages.2.labelMalePlural>
  <VFEI_VatGrownRoyalMaggot.lifeStages.2.labelFemale>RoyalMaggot</VFEI_VatGrownRoyalMaggot.lifeStages.2.labelFemale>
  <VFEI_VatGrownRoyalMaggot.lifeStages.2.labelFemalePlural>RoyalMaggot</VFEI_VatGrownRoyalMaggot.lifeStages.2.labelFemalePlural>
  <VFEI_VatGrownRoyalMaggot.labelMale>samiec RoyalMaggot</VFEI_VatGrownRoyalMaggot.labelMale>
  <VFEI_VatGrownRoyalMaggot.labelMalePlural>samce RoyalMaggot</VFEI_VatGrownRoyalMaggot.labelMalePlural>
  <VFEI_VatGrownRoyalMaggot.labelFemale>samica RoyalMaggot</VFEI_VatGrownRoyalMaggot.labelFemale>
  <VFEI_VatGrownRoyalMaggot.labelFemalePlural>samice RoyalMaggot</VFEI_VatGrownRoyalMaggot.labelFemalePlural>


</LanguageData>